varpepdb/__init__.py
varpepdb/classes.py
varpepdb/core.py
varpepdb/utils.py
varpepdb-1.0.4.dist-info/licenses/LICENSE
varpepdb-1.0.4.dist-info/METADATA
varpepdb-1.0.4.dist-info/WHEEL
varpepdb-1.0.4.dist-info/top_level.txt
varpepdb-1.0.4.dist-info/RECORD
