Metadata-Version: 2.4
Name: varpepdb
Version: 1.0.4
Summary: Generate reference database of variant peptides for peptide spectrum matching
Author-email: Jaren Junren Sia <siajunren@gmail.com>
License: MIT License
Project-URL: Homepage, https://github.com/jsialar/varpepdb
Keywords: proteomics,forensics,fasta,peptide,variant
Classifier: Programming Language :: Python
Classifier: Programming Language :: Python :: 3
Classifier: Operating System :: OS Independent
Classifier: Topic :: Scientific/Engineering
Classifier: Topic :: Scientific/Engineering :: Bio-Informatics
Requires-Python: >=3.8
License-File: LICENSE
Requires-Dist: rpg
Dynamic: license-file
